YizhongZhenduiTedingWangzhanLeibieDeWangyeZhiwenshibieFangfaNanyouCn105281973a/README.md
YizhongZhenduiTedingWangzhanLeibieDeWangyeZhiwenshibieFangfaNanyouCn105281973a/__init__.py
YizhongZhenduiTedingWangzhanLeibieDeWangyeZhiwenshibieFangfaNanyouCn105281973a/__main__.py
YizhongZhenduiTedingWangzhanLeibieDeWangyeZhiwenshibieFangfaNanyouCn105281973a/file.pdf
YizhongZhenduiTedingWangzhanLeibieDeWangyeZhiwenshibieFangfaNanyouCn105281973a/index.html
yizhong_zhendui_teding_wangzhan_leibie_de_wangye_zhiwenshibie_fangfa_nanyou_cn105281973a-2024.3.2.0.dist-info/METADATA
yizhong_zhendui_teding_wangzhan_leibie_de_wangye_zhiwenshibie_fangfa_nanyou_cn105281973a-2024.3.2.0.dist-info/WHEEL
yizhong_zhendui_teding_wangzhan_leibie_de_wangye_zhiwenshibie_fangfa_nanyou_cn105281973a-2024.3.2.0.dist-info/entry_points.txt
yizhong_zhendui_teding_wangzhan_leibie_de_wangye_zhiwenshibie_fangfa_nanyou_cn105281973a-2024.3.2.0.dist-info/top_level.txt
yizhong_zhendui_teding_wangzhan_leibie_de_wangye_zhiwenshibie_fangfa_nanyou_cn105281973a-2024.3.2.0.dist-info/RECORD
